[
    {
        "id": "level1",
        "name": "Beggining",
        "map_image_path": "map1.png",
        "waypoints_path": "map1_waypoints.json",
        "waves_path": "waves_level1.json",
        "thumbnail_path": "level1_thumb.png",
        "unlocked": true,
        "start_gold": 200,
        "start_wood": 100,
        "start_metal": 50,
        "are_abilities_enabled": false,
        "available_towers": [
            "basic",
            "rapid"
        ]
    },
    {
        "id": "level2",
        "name": "x",
        "map_image_path": "map2.png",
        "waypoints_path": "map2_waypoints.json",
        "waves_path": "waves_level2.json",
        "thumbnail_path": "level2_thumb.png",
        "unlocked": true,
        "start_gold": 250,
        "start_wood": 100,
        "start_metal": 50,
        "are_abilities_enabled": true,
        "available_towers": [
            "basic",
            "sniper",
            "cannon",
            "rapid"
        ]
    },
    {
        "id": "level3",
        "name": "hexagon valley",
        "map_image_path": "map3.png",
        "waypoints_path": "map3_waypoints.json",
        "waves_path": "waves_level3.json",
        "thumbnail_path": "level3_thumb.png",
        "unlocked": true,
        "start_gold": 300,
        "start_wood": 100,
        "start_metal": 50,
        "are_abilities_enabled": true,
        "available_towers": [
            "basic",
            "rapid",
            "sniper",
            "cannon",
            "flame",
            "ice"
        ]
    }
]